mqtt_io/__init__.py
mqtt_io/__main__.py
mqtt_io/config/__init__.py
mqtt_io/config/config.schema.yml
mqtt_io/config/validation/__init__.py
mqtt_io/config/validation/gpio.py
mqtt_io/config.sockets.yml
mqtt_io/constants.py
mqtt_io/events.py
mqtt_io/exceptions.py
mqtt_io/home_assistant.py
mqtt_io/modules/__init__.py
mqtt_io/modules/gpio/__init__.py
mqtt_io/modules/gpio/beaglebone.py
mqtt_io/modules/gpio/dockerpi.py
mqtt_io/modules/gpio/gpiod.py
mqtt_io/modules/gpio/gpiozero.py
mqtt_io/modules/gpio/mcp23017.py
mqtt_io/modules/gpio/mock.py
mqtt_io/modules/gpio/orangepi.py
mqtt_io/modules/gpio/pcf8574.py
mqtt_io/modules/gpio/pcf8575.py
mqtt_io/modules/gpio/piface2.py
mqtt_io/modules/gpio/raspberrypi.py
mqtt_io/modules/gpio/stdio.py
mqtt_io/modules/gpio/sunxi.py
mqtt_io/modules/gpio/xl9535.py
mqtt_io/modules/sensor/__init__.py
mqtt_io/modules/sensor/ads1x15.py
mqtt_io/modules/sensor/adxl345.py
mqtt_io/modules/sensor/aht20.py
mqtt_io/modules/sensor/as3935.py
mqtt_io/modules/sensor/bh1750.py
mqtt_io/modules/sensor/bme280.py
mqtt_io/modules/sensor/bme680.py
mqtt_io/modules/sensor/bmp085.py
mqtt_io/modules/sensor/dht22.py
mqtt_io/modules/sensor/ds18b.py
mqtt_io/modules/sensor/ens160.py
mqtt_io/modules/sensor/flowsensor.py
mqtt_io/modules/sensor/frequencycounter.py
mqtt_io/modules/sensor/hcsr04.py
mqtt_io/modules/sensor/ina219.py
mqtt_io/modules/sensor/lm75.py
mqtt_io/modules/sensor/mcp3008.py
mqtt_io/modules/sensor/mcp3xxx.py
mqtt_io/modules/sensor/mhz19.py
mqtt_io/modules/sensor/mock.py
mqtt_io/modules/sensor/pms5003.py
mqtt_io/modules/sensor/sht4x.py
mqtt_io/modules/sensor/tsl2561.py
mqtt_io/modules/sensor/veml6075.py
mqtt_io/modules/sensor/veml7700.py
mqtt_io/modules/stream/__init__.py
mqtt_io/modules/stream/pn532.py
mqtt_io/modules/stream/serial.py
mqtt_io/mqtt/__init__.py
mqtt_io/mqtt/aiomqtt.py
mqtt_io/server.py
mqtt_io/tests/features/config_main_invalid.feature
mqtt_io/tests/features/config_main_valid.feature
mqtt_io/tests/features/config_module_gpio_invalid.feature
mqtt_io-2.6.0.dist-info/LICENSE
mqtt_io-2.6.0.dist-info/METADATA
mqtt_io-2.6.0.dist-info/WHEEL
mqtt_io-2.6.0.dist-info/RECORD
