Metadata-Version: 2.1
Name: mqtt-io
Version: 2.6.0
Summary: Expose GPIO modules (Raspberry Pi, Beaglebone, PCF8754, PiFace2 etc.), digital sensors (LM75 etc.) and serial streams to an MQTT server for remote control and monitoring.
License: MIT
Author: Ellis Percival
Author-email: mqtt-io@failcode.co.uk
Requires-Python: >=3.8,<4.0
Classifier: License :: OSI Approved :: MIT License
Classifier: Programming Language :: Python :: 3
Classifier: Programming Language :: Python :: 3.8
Classifier: Programming Language :: Python :: 3.9
Classifier: Programming Language :: Python :: 3.10
Classifier: Programming Language :: Python :: 3.11
Classifier: Programming Language :: Python :: 3.12
Classifier: Programming Language :: Python :: 3.13
Requires-Dist: Cerberus (>=1.3.2,<2.0.0)
Requires-Dist: PyYAML (>=6.0.1,<7.0.0)
Requires-Dist: aiomqtt (>=2.1.0,<3.0.0)
Requires-Dist: backoff (>=2.2.1,<3.0.0)
Requires-Dist: confp (>=0.4.0,<0.5.0)
Requires-Dist: dataclasses (>=0.8,<0.9) ; python_version >= "3.6" and python_version < "3.7"
Requires-Dist: docutils (==0.18.1)
Requires-Dist: typing-extensions (>=4.4.0,<5.0.0)
Project-URL: Documentation, https://flyte.github.io/mqtt-io/
